pyclimaker/__init__.py
pyclimaker/exceptions.py
pyclimaker/utils.py
pyclimaker/argprompts/__init__.py
pyclimaker-0.5.dist-info/METADATA
pyclimaker-0.5.dist-info/WHEEL
pyclimaker-0.5.dist-info/top_level.txt
pyclimaker-0.5.dist-info/RECORD
