Metadata-Version: 2.1
Name: pyclimaker
Version: 0.5
Summary: A framework on which you can easily build a CLI just by adding functions (and a little bit more) to the boilerplate
Home-page: UNKNOWN
Author: Sanghun Kang
Author-email: sanghunkang.dev@gmail.com
License: UNKNOWN
Platform: UNKNOWN
